{
  "schema_version": "render_page.v1",
  "document_version": "",
  "page": {
    "id": "p0006",
    "title": "",
    "section_path": [],
    "source_page_number": 6
  },
  "nav": {
    "prev": "p0005",
    "next": "p0007",
    "parent_section": ""
  },
  "blocks": [
    {
      "kind": "paragraph",
      "id": "p0006.b001",
      "children": [
        {
          "kind": "text",
          "text": "ЗАКЛЮЧЕНИЕ",
          "marks": []
        },
        {
          "kind": "text",
          "text": "ПРОКЛЯТИЕ - СОН - ПРЕСТУПЛЕНИЕ",
          "marks": [
            "bold"
          ]
        },
        {
          "kind": "text",
          "text": "Вы можете уменьшить полученные Отбрасывания до 2. Вы можете уменьшить полученные Отталкивания на 1. Когда вы получаете Отбрасывание, вы можете потерять -1 . MNEMOSAG0138",
          "marks": []
        },
        {
          "kind": "text",
          "text": "M012",
          "marks": [
            "bold"
          ]
        },
        {
          "kind": "text",
          "text": "5467",
          "marks": []
        },
        {
          "kind": "text",
          "text": "M022",
          "marks": [
            "bold"
          ]
        },
        {
          "kind": "text",
          "text": "9123",
          "marks": []
        },
        {
          "kind": "text",
          "text": "M002",
          "marks": [
            "bold"
          ]
        },
        {
          "kind": "text",
          "text": "8 ЗАКЛЮЧЕНИЕ",
          "marks": []
        },
        {
          "kind": "text",
          "text": "Кто знает, сколько прошло времени? Темная, сырая, тесная и одинокая, камера не давала вам покоя. Лишь крошечная трещина в стене. ",
          "marks": [
            "italic"
          ]
        },
        {
          "kind": "text",
          "text": "Если вы двигаетесь добровольно, атакуете или используете действие или способность, встаньте. В начале вашего хода встаньте. Если эта карта сбрасывается другим эффектом, встаньте. СБИТ С НОГ (ВСТАВАНИЕ)",
          "marks": []
        },
        {
          "kind": "text",
          "text": "СОСТОЯНИЕ (ТЕЛО)",
          "marks": [
            "bold"
          ]
        },
        {
          "kind": "text",
          "text": "Поместите свою миниатюру в обычное положение и сбросьте эту карту. Вы сбиты с ног. Положите свою миниатюру на бок в качестве напоминания. Вы не можете двигаться добровольно, атаковать или использовать действия или способности, если не указано иное. Если эта карта сбрасывается другим эффектом, встаньте (см. другую сторону карты). В конце вашего следующего хода переверните эту карту. СБИТ С НОГ (ПАДЕНИЕ)",
          "marks": []
        },
        {
          "kind": "text",
          "text": "СОСТОЯНИЕ (ТЕЛО)",
          "marks": [
            "bold"
          ]
        },
        {
          "kind": "text",
          "text": "AL0303Получите 2 ресурса Вооружения.å______________________________ß",
          "marks": []
        },
        {
          "kind": "text",
          "text": "Осужденный-",
          "marks": [
            "bold"
          ]
        },
        {
          "kind": "text",
          "text": "Вместо этого получите 1 ресурс Вооружения. AB00862 Оружейный Склад ИССЛЕДОВАНИЕ+0Перепозиционируйте на 4 вместо этого. Перепозиционируйте на 2. Открытие X, где X — количество , которым вы попали.",
          "marks": []
        },
        {
          "kind": "text",
          "text": "Кость, НожКость, Нож",
          "marks": [
            "bold",
            "italic"
          ]
        },
        {
          "kind": "text",
          "text": "КИТОВЫЕ НОЖИ 3",
          "marks": []
        },
        {
          "kind": "text",
          "text": "5+",
          "marks": [
            "bold"
          ]
        },
        {
          "kind": "text",
          "text": "AJ0177",
          "marks": []
        },
        {
          "kind": "text",
          "text": "7 кубиков d101 Игровое Поле Битвы4 Трискелиона (с соединителями)166 карт Технологий (160 стандартных, 6 Таро)30 карт Мнемос25 карт Ландшафта27 карт Судьбоносных Мнемос41 карта Состояний126 карт Исследования64 карты Подсказок9 карт Рока15 карт Истории (Основная и Внутренняя Одиссея)382 карты Снаряжения",
          "marks": [
            "italic"
          ]
        },
        {
          "kind": "text",
          "text": "Вы, вероятно, заметили гигантскую миниатюру Гелиоса в коробке с игрой!",
          "marks": []
        },
        {
          "kind": "text",
          "text": "Это не Первозданный и не будет использоваться непосредственно в игровом процессе",
          "marks": [
            "bold"
          ]
        },
        {
          "kind": "text",
          "text": ", кроме как в качестве маркера. Это коллекционная миниатюра из невыпущенной линии смоляных фигурок, которую мы включили в игру, чтобы поблагодарить всех наших спонсоров за их поддержку и терпение, пока мы доставляли эту масштабную игру! Таким образом, миниатюра предназначена для замены (если вы того пожелаете!) оригинального картонного маркера Приоритетной Цели. Ее также можно использовать в качестве маркера Лидера Отряда во время приключений, чтобы продемонстрировать бремя ответственности! Гелиос наблюдает и судит!",
          "marks": []
        },
        {
          "kind": "text",
          "text": "Книга правил и Обучение игре",
          "marks": [
            "italic"
          ]
        },
        {
          "kind": "text",
          "text": "КОЛОННАПрепятствие. Затмевающее. Разрушаемое. ",
          "marks": []
        },
        {
          "kind": "text",
          "text": "Ловушка:",
          "marks": [
            "bold"
          ]
        },
        {
          "kind": "text",
          "text": "Если вы толкаете Первозданного на эту плитку, уберите плитку и бросьте d10: 1-2: Ничего не происходит. 3-8: Поместите 1 отрицательный жетон в Пул Кратоса. 9-10: Поместите 2 отрицательных жетона в Пул Кратоса. AI0361 ЛАНДШАФТ",
          "marks": []
        },
        {
          "kind": "text",
          "text": "НАСЛЕДИЕ - БОГИ - СУДЬБА",
          "marks": [
            "bold"
          ]
        },
        {
          "kind": "text",
          "text": "ПАМЯТЬ О СМЕРТИ",
          "marks": []
        },
        {
          "kind": "text",
          "text": "Этот момент навсегда запечатлен в вашей душе.",
          "marks": [
            "italic"
          ]
        },
        {
          "kind": "text",
          "text": "Во время Жребия Травмы, считайте ваш на 1 выше. СУДЬБОНОСНАЯ МНЕМОС AF0125 123 Последняя Академия Антидоктринальная Философия, Минойские Расследования, Охота на Титанов",
          "marks": []
        },
        {
          "kind": "text",
          "text": "ТЕХНОЛОГИЯ ТЕХНОЛОГИЯ СТРУКТУРНАЯ",
          "marks": [
            "bold"
          ]
        },
        {
          "kind": "text",
          "text": " РИТОРИКА ",
          "marks": []
        },
        {
          "kind": "text",
          "text": "Лабиринтийцы с набожной страстью говорят о небытии. Нам нужно свое собственное послание.",
          "marks": [
            "italic"
          ]
        },
        {
          "kind": "text",
          "text": "AA0033",
          "marks": []
        },
        {
          "kind": "text",
          "text": "Пусть все, кто сомневается в своем предназначении, не отчаиваются, ибо этот корабль сам по себе является посланием: мы здесь не просто так. ",
          "marks": [
            "italic"
          ]
        },
        {
          "kind": "text",
          "text": "Спасение.",
          "marks": [
            "bold"
          ]
        },
        {
          "kind": "text",
          "text": "Получите +1 , когда собираетесь получить , чтобы проверить Дипломатию (7+). Успех: Уменьшите это получение на 1 (минимум до 0).",
          "marks": []
        },
        {
          "kind": "text",
          "text": "Переговоры.",
          "marks": [
            "bold"
          ]
        },
        {
          "kind": "text",
          "text": "Получите +1 , чтобы потерять -1 .",
          "marks": []
        },
        {
          "kind": "text",
          "text": "ТЕХНОЛОГИЯ ТЕХНОЛОГИЯ СТРАНСТВИЕ - ТОЛЬКО ЦИКЛ I",
          "marks": [
            "bold"
          ]
        },
        {
          "kind": "text",
          "text": " РИТОРИКА ",
          "marks": []
        },
        {
          "kind": "text",
          "text": "13 кастомных кубиков d6",
          "marks": [
            "italic"
          ]
        },
        {
          "kind": "icon",
          "symbol_id": "sym.board_tile_n",
          "alt": "Board_tile_n"
        }
      ]
    }
  ],
  "figures": {},
  "glossary_mentions": [
    "concept.board_tile_n"
  ],
  "search": {},
  "source_map": {
    "page_id": "p0006",
    "block_refs": [
      "p0006.b001"
    ]
  },
  "build_meta": null
}