{
  "schema_version": "render_page.v1",
  "document_version": "",
  "page": {
    "id": "p0063",
    "title": "Ограниченные способности и эффекты",
    "section_path": [],
    "source_page_number": 63
  },
  "nav": {
    "prev": "p0062",
    "next": "p0064",
    "parent_section": ""
  },
  "blocks": [
    {
      "kind": "paragraph",
      "id": "p0063.b001",
      "children": [
        {
          "kind": "text",
          "text": "Пример:",
          "marks": [
            "bold",
            "italic"
          ]
        },
        {
          "kind": "text",
          "text": " У Геймченджера есть способность Титана под названием ",
          "marks": [
            "italic"
          ]
        },
        {
          "kind": "text",
          "text": "Продвинутый Рефлекс",
          "marks": [
            "bold",
            "italic"
          ]
        },
        {
          "kind": "text",
          "text": ", а также карта «Спасатель Япета» со способностью ",
          "marks": [
            "italic"
          ]
        },
        {
          "kind": "text",
          "text": "Рефлекс",
          "marks": [
            "bold",
            "italic"
          ]
        },
        {
          "kind": "text",
          "text": ". Несмотря на то, что одна из них имеет подтип (Продвинутый), а другая нет, они все равно называются одинаково, и поэтому обе не могут быть использованы в одном и том же раунде. Геймченджер должен выбрать, какую из них использовать. Однако, если в том же раунде есть другая способность, игрок, контролирующий Титана, может выбрать использование другой способности.",
          "marks": [
            "italic"
          ]
        }
      ]
    },
    {
      "kind": "heading",
      "id": "p0063.b002",
      "level": 2,
      "children": [
        {
          "kind": "text",
          "text": "Ограниченные способности и эффекты",
          "marks": []
        }
      ]
    },
    {
      "kind": "paragraph",
      "id": "p0063.b003",
      "children": [
        {
          "kind": "text",
          "text": "Многие способности и эффекты карт, а также карты Мнемос, планшеты Титанов и другие игровые элементы разблокируются при выполнении других требований, обычно при наличии достаточно высокого уровня ",
          "marks": []
        },
        {
          "kind": "text",
          "text": "Опасности",
          "marks": [
            "bold"
          ]
        },
        {
          "kind": "text",
          "text": ". Подробнее см. на стр. 46. ",
          "marks": []
        }
      ]
    },
    {
      "kind": "heading",
      "id": "p0063.b004",
      "level": 2,
      "children": [
        {
          "kind": "text",
          "text": "Способности Первозданных",
          "marks": []
        }
      ]
    },
    {
      "kind": "paragraph",
      "id": "p0063.b005",
      "children": [
        {
          "kind": "text",
          "text": "Ограничения, касающиеся использования способностей, не распространяются на Первозданных. Разрешайте способности Первозданных каждый раз, когда вам это предписывает карта ИИ или БП, свойство или любой другой игровой элемент. Все способности на картах БП и ИИ разрешаются ",
          "marks": []
        },
        {
          "kind": "text",
          "text": "Первозданным",
          "marks": [
            "bold"
          ]
        },
        {
          "kind": "text",
          "text": " ",
          "marks": []
        },
        {
          "kind": "text",
          "text": "против",
          "marks": [
            "bold"
          ]
        },
        {
          "kind": "text",
          "text": " Титана — Цели (в случае Атаки) или Атакующего (в случае Ответа) — если явно не указано иное.",
          "marks": []
        }
      ]
    },
    {
      "kind": "heading",
      "id": "p0063.b006",
      "level": 2,
      "children": [
        {
          "kind": "text",
          "text": "Истощение, сброс и удаление",
          "marks": []
        }
      ]
    },
    {
      "kind": "paragraph",
      "id": "p0063.b007",
      "children": [
        {
          "kind": "text",
          "text": "Многие эффекты предписывают вам истощить, сбросить или удалить элемент. Обычно ",
          "marks": []
        },
        {
          "kind": "text",
          "text": "истощение",
          "marks": [
            "bold"
          ]
        },
        {
          "kind": "text",
          "text": " является временным эффектом, тогда как ",
          "marks": []
        },
        {
          "kind": "text",
          "text": "сброс",
          "marks": [
            "bold"
          ]
        },
        {
          "kind": "text",
          "text": " более постоянен. ",
          "marks": []
        },
        {
          "kind": "text",
          "text": "Удаление",
          "marks": [
            "bold"
          ]
        },
        {
          "kind": "text",
          "text": " (или архивирование) игрового элемента из игры означает его возвращение в коробку с игрой. Он не будет использоваться снова, если явно не указано иное.",
          "marks": []
        }
      ]
    },
    {
      "kind": "heading",
      "id": "p0063.b008",
      "level": 2,
      "children": [
        {
          "kind": "text",
          "text": "Истощение",
          "marks": []
        }
      ]
    },
    {
      "kind": "paragraph",
      "id": "p0063.b009.0",
      "children": [
        {
          "kind": "text",
          "text": "Когда вам предписано ",
          "marks": []
        },
        {
          "kind": "text",
          "text": "истощить",
          "marks": [
            "bold"
          ]
        },
        {
          "kind": "text",
          "text": " карту, вы должны повернуть ее на 90 градусов вправо, чтобы обозначить это. Она по-прежнему считается экипированной на вашем Титане или Аргонавте, но вы не можете использовать ее как активное оружие, использовать ее защитные характеристики или активировать какие-либо ее способности, кроме эффектов, вызванных истощением (например, «если истощена») или эффектов, приводящих к ее восстановлению (например, «Когда вы сбиты с ног, восстановите эту карту»). ",
          "marks": []
        }
      ]
    },
    {
      "kind": "paragraph",
      "id": "p0063.b009.1.0",
      "children": [
        {
          "kind": "text",
          "text": "Примечание: ",
          "marks": [
            "bold"
          ]
        },
        {
          "kind": "text",
          "text": "Пассивные способности (такие как Дальность 2-4 или +1 Точность) являются постоянными, поэтому они остаются в силе, даже если карта, на которой они напечатаны, истощена. Аналогично, свойства всегда активны. Карты остаются истощенными, пока они не будут восстановлены другим эффектом (см. ниже).",
          "marks": []
        },
        {
          "kind": "text",
          "text": "Пример истощения",
          "marks": [
            "italic"
          ]
        },
        {
          "kind": "text",
          "text": "Некоторые игровые элементы, помимо карт, могут предписывать вам их истощить. В этом случае вы истощаете только этот конкретный игровой элемент. ",
          "marks": []
        }
      ]
    },
    {
      "kind": "paragraph",
      "id": "p0063.b009.1.1",
      "children": [
        {
          "kind": "text",
          "text": "Например, если ",
          "marks": []
        },
        {
          "kind": "text",
          "text": "истощение",
          "marks": [
            "bold"
          ]
        },
        {
          "kind": "text",
          "text": " является стоимостью способности Титана, описанной на планшете Титана, вы должны истощить ",
          "marks": []
        },
        {
          "kind": "text",
          "text": "только эту способность",
          "marks": [
            "bold"
          ]
        },
        {
          "kind": "text",
          "text": ". Поместите общий жетон на эту способность в качестве напоминания о том, что она истощена, но это не отменяет никаких других способностей Титана или Таблицы Кратоса. Все игровые элементы остаются истощенными, пока они не будут восстановлены другим эффектом (см. ниже).",
          "marks": []
        }
      ]
    },
    {
      "kind": "heading",
      "id": "p0063.b010",
      "level": 2,
      "children": [
        {
          "kind": "text",
          "text": "Восстановление",
          "marks": []
        }
      ]
    },
    {
      "kind": "paragraph",
      "id": "p0063.b011",
      "children": [
        {
          "kind": "text",
          "text": "Каждый Аргонавт может потратить свое ",
          "marks": []
        },
        {
          "kind": "text",
          "text": "действие передвижения",
          "marks": [
            "bold"
          ]
        },
        {
          "kind": "text",
          "text": " или",
          "marks": []
        },
        {
          "kind": "text",
          "text": " боевое действие",
          "marks": [
            "bold"
          ]
        },
        {
          "kind": "text",
          "text": ", чтобы ",
          "marks": []
        },
        {
          "kind": "text",
          "text": "восстановить все истощенные экипированные игровые элементы ",
          "marks": [
            "bold"
          ]
        },
        {
          "kind": "text",
          "text": "(карты, карты Мнемос, способности Титанов и так далее). Некоторые другие игровые эффекты также могут позволить вам восстановить некоторые или все ваши игровые элементы.",
          "marks": []
        }
      ]
    },
    {
      "kind": "heading",
      "id": "p0063.b012",
      "level": 2,
      "children": [
        {
          "kind": "text",
          "text": "Истощаемое Снаряжение",
          "marks": []
        }
      ]
    },
    {
      "kind": "paragraph",
      "id": "p0063.b013",
      "children": [
        {
          "kind": "text",
          "text": "Некоторые игровые эффекты относятся к ",
          "marks": []
        },
        {
          "kind": "text",
          "text": "Истощаемому",
          "marks": [
            "bold"
          ]
        },
        {
          "kind": "text",
          "text": " Снаряжению. Эта категория включает все карты с ключевым словом «Громоздкий» или с активными способностями, которые включают истощение в качестве своей стоимости.",
          "marks": []
        }
      ]
    },
    {
      "kind": "heading",
      "id": "p0063.b014",
      "level": 2,
      "children": [
        {
          "kind": "text",
          "text": "Сброс",
          "marks": []
        }
      ]
    },
    {
      "kind": "paragraph",
      "id": "p0063.b015",
      "children": [
        {
          "kind": "text",
          "text": "Когда игра предписывает вам ",
          "marks": []
        },
        {
          "kind": "text",
          "text": "сбросить",
          "marks": [
            "bold"
          ]
        },
        {
          "kind": "text",
          "text": " жетон, верните его в запас жетонов. Когда вам предписано ",
          "marks": []
        },
        {
          "kind": "text",
          "text": "сбросить",
          "marks": [
            "bold"
          ]
        },
        {
          "kind": "text",
          "text": " или карту Мнемос, переверните ее лицевой стороной вниз. Она непригодна до конца этой Битвы и не считается экипированной вашим Титаном или Аргонавтом. Однако она не удаляется из игры навсегда – она остается в Оружейной Арго (в случае карт) или назначенной вашим Аргонавтам (в случае карт Мнемос) и может быть использована в будущих Битвах.",
          "marks": []
        }
      ]
    },
    {
      "kind": "heading",
      "id": "p0063.b016",
      "level": 2,
      "children": [
        {
          "kind": "text",
          "text": "Удаление элементов (архивирование)",
          "marks": []
        }
      ]
    },
    {
      "kind": "paragraph",
      "id": "p0063.b017.0",
      "children": [
        {
          "kind": "text",
          "text": "Когда вам предписано навсегда удалить элемент из игры, верните его в коробку с игрой. Вероятно, он не будет использоваться в вашей текущей кампании, если только будущий эффект явно не сошлется на этот элемент. Постоянное удаление элемента иногда может называться ",
          "marks": []
        },
        {
          "kind": "text",
          "text": "Архивированием",
          "marks": [
            "bold"
          ]
        },
        {
          "kind": "text",
          "text": " игрового элемента. Иногда вам может быть предписано удалить элемент на определенный срок. В таком случае отложите его в сторону и держите отдельно от других игровых элементов на этот срок. ",
          "marks": []
        }
      ]
    },
    {
      "kind": "paragraph",
      "id": "p0063.b017.1.0",
      "children": [
        {
          "kind": "text",
          "text": "Например, когда предписано удалить элемент из Битвы, он удаляется из ",
          "marks": []
        },
        {
          "kind": "text",
          "text": "только этой Битвы",
          "marks": [
            "bold"
          ]
        },
        {
          "kind": "text",
          "text": ", но будет использоваться в последующих Битвах против того же Первозданного. Аналогично, если карта Исследования удаляется до следующей Битвы на Временной шкале, она должна быть удалена из колоды Исследования, затем замешана обратно в нее в Послесловии следующей Битвы на Временной шкале (как указано в Сценарии Битвы). ",
          "marks": []
        },
        {
          "kind": "text",
          "text": "Примечание:",
          "marks": [
            "bold"
          ]
        },
        {
          "kind": "text",
          "text": " Постоянное удаление элемента из игры — крайне редкое явление и всегда будет специально оговариваться. ",
          "marks": []
        }
      ]
    },
    {
      "kind": "paragraph",
      "id": "p0063.b017.1.1",
      "children": [
        {
          "kind": "text",
          "text": "Если эффект явно не указывает, что элемент должен быть навсегда удален из игры, то это не так.",
          "marks": []
        }
      ]
    },
    {
      "kind": "heading",
      "id": "p0063.b018",
      "level": 2,
      "children": [
        {
          "kind": "text",
          "text": "Усталость",
          "marks": []
        }
      ]
    },
    {
      "kind": "paragraph",
      "id": "p0063.b019",
      "children": [
        {
          "kind": "text",
          "text": "Некоторые мощные способности и эффекты могут потребовать от вас получить жетон ",
          "marks": []
        },
        {
          "kind": "text",
          "text": "усталости от передвижения",
          "marks": [
            "bold"
          ]
        },
        {
          "kind": "text",
          "text": " или ",
          "marks": []
        },
        {
          "kind": "text",
          "text": "усталости от боя",
          "marks": [
            "bold"
          ]
        },
        {
          "kind": "text",
          "text": " . Пока у вас есть жетон усталости, вы можете использовать соответствующее действие ",
          "marks": []
        },
        {
          "kind": "text",
          "text": "только для сброса этого жетона",
          "marks": [
            "bold"
          ]
        },
        {
          "kind": "text",
          "text": ". Это единственный способ сбросить этот жетон. Вы не можете получить жетон усталости, если у вас уже есть один. После того как вы сбросите жетон усталости, если у вас остались какие-либо действия, вы можете выполнить их как обычно. ",
          "marks": []
        },
        {
          "kind": "text",
          "text": "Жетон усталости от передвиженияЖетон усталости от боя",
          "marks": [
            "italic"
          ]
        }
      ]
    },
    {
      "kind": "figure",
      "id": "p0063.fig.p0063.img0000",
      "asset_id": "p0063.img0000",
      "children": []
    },
    {
      "kind": "figure",
      "id": "p0063.fig.p0063.img0001",
      "asset_id": "p0063.img0001",
      "children": []
    },
    {
      "kind": "figure",
      "id": "p0063.fig.p0063.img0002",
      "asset_id": "p0063.img0002",
      "children": []
    },
    {
      "kind": "figure",
      "id": "p0063.fig.p0063.img0003",
      "asset_id": "p0063.img0003",
      "children": []
    }
  ],
  "figures": {
    "p0063.img0000": {
      "src": "/documents/ato_core_v1_1/images/p0063.img0000.jpeg",
      "alt": "p0063.img0000"
    },
    "p0063.img0001": {
      "src": "/documents/ato_core_v1_1/images/p0063.img0001.jpeg",
      "alt": "p0063.img0001"
    },
    "p0063.img0002": {
      "src": "/documents/ato_core_v1_1/images/p0063.img0002.jpeg",
      "alt": "p0063.img0002"
    },
    "p0063.img0003": {
      "src": "/documents/ato_core_v1_1/images/p0063.img0003.jpeg",
      "alt": "p0063.img0003"
    }
  },
  "glossary_mentions": [
    "concept.art_texture_light_a"
  ],
  "search": {},
  "source_map": {
    "page_id": "p0063",
    "block_refs": [
      "p0063.b001",
      "p0063.b002",
      "p0063.b003",
      "p0063.b004",
      "p0063.b005",
      "p0063.b006",
      "p0063.b007",
      "p0063.b008",
      "p0063.b009",
      "p0063.b010",
      "p0063.b011",
      "p0063.b012",
      "p0063.b013",
      "p0063.b014",
      "p0063.b015",
      "p0063.b016",
      "p0063.b017",
      "p0063.b018",
      "p0063.b019"
    ]
  },
  "build_meta": null
}